{
  "project_name": "WNET5q5h6u6l4",
  "generated_at": "2026-04-10T12:56:24.215341+08:00",
  "status": "partial",
  "calculation_standard": "ablation-study-v1",
  "sources": {
    "training_info": true,
    "compute_analysis": false,
    "model_info": true,
    "linear_response": true,
    "linearity_by_frequency": false,
    "config": true
  },
  "missing_sources": [
    "compute_analysis.json",
    "linearity_by_frequency.json"
  ],
  "missing_sections": [
    "training_info.evaluation_metrics"
  ],
  "epochs": 30000,
  "min_loss": 0.017097,
  "min_val_loss": 0.018799,
  "train_loss": null,
  "val_loss": null,
  "train_mae": null,
  "train_afmae": null,
  "val_mae": null,
  "val_afmae": null,
  "weights_source": null,
  "freq_drift_hz": 1.6740971909791185,
  "sens_drift_percent": 5.496093224028378,
  "linearity_percent": null,
  "compute_cost": null,
  "total_params": 8023,
  "lr": 0.02,
  "use_cosine_annealing": null,
  "metric_details": {
    "natural_frequency_drift": {
      "min": 33.72998842278009,
      "max": 35.85511293271555,
      "median": 34.18101574173643,
      "count": 25,
      "unit": "Hz",
      "method": "max(|max-median|, |median-min|) from fn_comped",
      "drift": 1.6740971909791185
    },
    "sensitivity_drift": {
      "min": 60.13309097674453,
      "max": 67.86898408437395,
      "median": 65.62918420077291,
      "count": 25,
      "unit": "%",
      "method": "max(|max-median|, |median-min|) from interpolated sensitivity",
      "drift": 5.496093224028378,
      "frequency_hz": 100.0
    },
    "linearity": null,
    "natural_frequency_drift_origin": {
      "min": 34.24511189190977,
      "max": 93.39109037552112,
      "median": 58.893451232916746,
      "count": 25,
      "unit": "Hz",
      "method": "max(|max-median|, |median-min|) from fn_origin",
      "drift": 34.49763914260437
    },
    "sensitivity_drift_origin": {
      "min": 60.00193475436049,
      "max": 203.37127543371568,
      "median": 144.56283404568921,
      "count": 25,
      "unit": "%",
      "method": "max(|max-median|, |median-min|) from interpolated origin sensitivity",
      "drift": 84.56089929132872,
      "frequency_hz": 100.0
    },
    "linearity_origin": null
  },
  "compute_details": null,
  "display_metrics": {
    "TRAIN_MAE": null,
    "TRAIN_AFMAE": null,
    "VAL_MAE": null,
    "VAL_AFMAE": null,
    "Freq Drift (Hz)": 1.6740971909791185,
    "Sens Drift (%)": 5.496093224028378,
    "Linearity (%)": null,
    "Compute Cost": null,
    "Total Params": 8023,
    "Epochs": 30000,
    "LR": 0.02,
    "Cosine Annealing": null
  }
}