{
  "valDatasetFreqRange": "10--200~Hz sampled grid; evaluation band $/leq 128$~Hz",
  "valDatasetMagnitudeRange": "0.24--6.0 m/s2",
  "valDatasetPreprocess": "steady-state clipping, two-window slicing, and normalization to [-1, 1]",
  "valDatasetScenarioMapping": "frequency--magnitude matrix with paired measured and ideal waveforms",
  "valDatasetSplit": "50/%/50/% training/validation split",
  "valDatasetTotalRecords": "350 frequency--magnitude operating points",
  "valTargetCurveSource": "ideal second-order response fitted from the low-magnitude calibration sweep",
  "valOpenDataPackage": "processed response matrix and plotting scripts are available with the manuscript materials",
  "valOpenCodePackage": "analysis and plotting code are available with the manuscript materials",
  "valWienerParallelAmpCount": "25",
  "valWienerParallelCfMae": "1.87",
  "valWienerParallelCfRmse": "2.34",
  "valWienerParallelGainFreq": "100",
  "valWienerParallelGainMae": "4.53",
  "valWienerParallelGainRmse": "5.53",
  "valExternalSensorPlan": "repeat the frequency--magnitude matrix on a second MET sample",
  "valExternalExcitationPlan": "repeat the protocol on an independent shaker table",
  "valAblationOverviewRowCount": "10",
  "valMainCNNFreqDrift": "3.72",
  "valMainCNNSensDrift": "16.24",
  "valMainCNNLinearity": "0.920",
  "valMainCNNKeilFps": "2009.9",
  "valMainCNNKeilRamKB": "50.9",
  "valMainCNNParams": "885",
  "valMainTCNFreqDrift": "2.65",
  "valMainTCNSensDrift": "16.08",
  "valMainTCNLinearity": "0.517",
  "valMainTCNKeilFps": "935.7",
  "valMainTCNKeilRamKB": "106.7",
  "valMainTCNParams": "1,697",
  "valMainRNNFreqDrift": "6.68",
  "valMainRNNSensDrift": "23.75",
  "valMainRNNLinearity": "0.726",
  "valMainRNNKeilFps": "3652.9",
  "valMainRNNKeilRamKB": "58.7",
  "valMainRNNParams": "577",
  "valMainGRUFreqDrift": "7.40",
  "valMainGRUSensDrift": "27.15",
  "valMainGRULinearity": "0.726",
  "valMainGRUKeilFps": "1660.1",
  "valMainGRUKeilRamKB": "58.7",
  "valMainGRUParams": "1,201",
  "valMainLSTMFreqDrift": "4.50",
  "valMainLSTMSensDrift": "13.80",
  "valMainLSTMLinearity": "0.512",
  "valMainLSTMKeilFps": "1426.3",
  "valMainLSTMKeilRamKB": "58.7",
  "valMainLSTMParams": "1,441",
  "valMainLSTMTransformerFreqDrift": "4.72",
  "valMainLSTMTransformerSensDrift": "18.38",
  "valMainLSTMTransformerLinearity": "0.567",
  "valMainLSTMTransformerKeilFps": "1461.5",
  "valMainLSTMTransformerKeilRamKB": "83.7",
  "valMainLSTMTransformerParams": "1,261",
  "valMainWienerKANFreqDrift": "2.34",
  "valMainWienerKANSensDrift": "9.09",
  "valMainWienerKANLinearity": "0.511",
  "valMainWienerKANKeilFps": "6986.7",
  "valMainWienerKANKeilRamKB": "5.6",
  "valMainWienerKANParams": "2,569",
  "valPrimaryProject": "FRIKANh8u6l6/_e1k/_lr7e4",
  "valPrimaryFreqDrift": "2.34",
  "valPrimarySensDrift": "9.09",
  "valPrimaryLinearity": "0.511",
  "valPrimaryKeilFps": "6986.7",
  "valPrimaryKeilRamKB": "5.6",
  "valPrimaryParams": "2,569",
  "valFreqScanPoints": "14",
  "valMagScanPoints": "25",
  "valDatasetOperatingPoints": "350",
  "valDatasetPointsPerRecord": "8000",
  "valDatasetWindowPoints": "8000",
  "valDatasetWindowRecords": "350",
  "valDatasetTrainRecords": "175",
  "valDatasetValRecords": "175",
  "valDatasetSplitUnit": "frequency--magnitude operating points after steady-state clipping",
  "valEpochs": "1000",
  "valInitLR": "0.0007",
  "valLearningRateSchedule": "fixed learning rate",
  "valMainWienerParams": "-",
  "valMainWienerFreqDrift": "34.50",
  "valMainWienerSensDrift": "84.56",
  "valMainWienerLinearity": "2.004",
  "valLossMAEFreqDrift": "13.00",
  "valLossMAESensDrift": "20.28",
  "valLossMAELinearity": "0.793",
  "valLossMAEKeilFps": "6986.7",
  "valLossMAEKeilRamKB": "5.6",
  "valLossMAEParams": "2,569",
  "valLossMAEEpoch": "975",
  "valLossAFMAEFreqDrift": "4.00",
  "valLossAFMAESensDrift": "21.06",
  "valLossAFMAELinearity": "1.068",
  "valLossAFMAEKeilFps": "6986.7",
  "valLossAFMAEKeilRamKB": "5.6",
  "valLossAFMAEParams": "2,569",
  "valLossAFMAEEpoch": "934",
  "valLossJointFreqDrift": "2.34",
  "valLossJointSensDrift": "9.09",
  "valLossJointLinearity": "0.511",
  "valLossJointKeilFps": "6986.7",
  "valLossJointKeilRamKB": "5.6",
  "valLossJointParams": "2,569",
  "valLossJointEpoch": "957",
  "valConFullFreqDrift": "2.34",
  "valConFullSensDrift": "9.09",
  "valConFullLinearity": "0.511",
  "valConFullKeilFps": "6986.7",
  "valConFullKeilRamKB": "-",
  "valConFullParams": "2,569",
  "valConUnconFreqDrift": "10.91",
  "valConUnconSensDrift": "10.61",
  "valConUnconLinearity": "2.109",
  "valConUnconKeilFps": "-",
  "valConUnconKeilRamKB": "-",
  "valConUnconParams": "2,569",
  "valConOddFreqDrift": "58.03",
  "valConOddSensDrift": "50.87",
  "valConOddLinearity": "38.586",
  "valConOddKeilFps": "-",
  "valConOddKeilRamKB": "-",
  "valConOddParams": "2,569",
  "valConPosFreqDrift": "2.43",
  "valConPosSensDrift": "9.22",
  "valConPosLinearity": "0.883",
  "valConPosKeilFps": "-",
  "valConPosKeilRamKB": "-",
  "valConPosParams": "2,425",
  "valFreqYesYesFreqDrift": "2.34",
  "valFreqYesYesSensDrift": "9.09",
  "valFreqYesYesLinearity": "0.511",
  "valFreqYesYesKeilFps": "6986.7",
  "valFreqYesYesKeilRamKB": "-",
  "valFreqYesYesParams": "2,569",
  "valFreqNoYesFreqDrift": "5.34",
  "valFreqNoYesSensDrift": "21.38",
  "valFreqNoYesLinearity": "3.216",
  "valFreqNoYesKeilFps": "-",
  "valFreqNoYesKeilRamKB": "-",
  "valFreqNoYesParams": "2,569",
  "valFreqYesNoFreqDrift": "5.82",
  "valFreqYesNoSensDrift": "27.48",
  "valFreqYesNoLinearity": "0.782",
  "valFreqYesNoKeilFps": "-",
  "valFreqYesNoKeilRamKB": "-",
  "valFreqYesNoParams": "2,493",
  "valFreqNoNoFreqDrift": "2.43",
  "valFreqNoNoSensDrift": "9.22",
  "valFreqNoNoLinearity": "0.883",
  "valFreqNoNoKeilFps": "-",
  "valFreqNoNoKeilRamKB": "-",
  "valFreqNoNoParams": "2,425",
  "valActBSplineFreqDrift": "2.34",
  "valActBSplineSensDrift": "9.09",
  "valActBSplineLinearity": "0.511",
  "valActBSplineKeilFps": "6986.7",
  "valActBSplineKeilRamKB": "-",
  "valActBSplineParams": "2,569",
  "valActReLUFreqDrift": "2.43",
  "valActReLUSensDrift": "9.22",
  "valActReLULinearity": "0.883",
  "valActReLUKeilFps": "-",
  "valActReLUKeilRamKB": "-",
  "valActReLUParams": "2,425",
  "valActTanhFreqDrift": "5.82",
  "valActTanhSensDrift": "27.48",
  "valActTanhLinearity": "0.782",
  "valActTanhKeilFps": "-",
  "valActTanhKeilRamKB": "-",
  "valActTanhParams": "2,493",
  "valActSigmoidFreqDrift": "10.91",
  "valActSigmoidSensDrift": "10.61",
  "valActSigmoidLinearity": "2.109",
  "valActSigmoidKeilFps": "-",
  "valActSigmoidKeilRamKB": "-",
  "valActSigmoidParams": "2,569",
  "valIirBaseEpoch": "1000",
  "valIirBaseFreqDrift": "2.34",
  "valIirBaseSensDrift": "9.09",
  "valIirBaseLinearity": "0.511",
  "valIirBaseKeilFps": "6986.7",
  "valIirBaseKeilRamKB": "-",
  "valIirBaseParams": "2,569",
  "valIirRandomFrozenEpoch": "1000",
  "valIirRandomFrozenFreqDrift": "5.37",
  "valIirRandomFrozenSensDrift": "22.28",
  "valIirRandomFrozenLinearity": "1.308",
  "valIirRandomFrozenKeilFps": "-",
  "valIirRandomFrozenKeilRamKB": "-",
  "valIirRandomFrozenParams": "2,569",
  "valIirSystemTrainableEpoch": "251",
  "valIirSystemTrainableFreqDrift": "94.87",
  "valIirSystemTrainableSensDrift": "64.68",
  "valIirSystemTrainableLinearity": "7.478",
  "valIirSystemTrainableKeilFps": "-",
  "valIirSystemTrainableKeilRamKB": "-",
  "valIirSystemTrainableParams": "2,569",
  "valIirRandomTrainableEpoch": "1000",
  "valIirRandomTrainableFreqDrift": "102.57",
  "valIirRandomTrainableSensDrift": "16.65",
  "valIirRandomTrainableLinearity": "5.144",
  "valIirRandomTrainableKeilFps": "-",
  "valIirRandomTrainableKeilRamKB": "-",
  "valIirRandomTrainableParams": "2,569",
  "valDeployRawQemu": "7.114e-03",
  "valDeployRawKeilFps": "6986.7",
  "valDeployRawMae": "7.114e-03",
  "valDeployRawRamKB": "5.6",
  "valDeployGRUQemu": "2.451e-03",
  "valDeployGRUKeilFps": "1660.1",
  "valDeployGRUMae": "2.451e-03",
  "valDeployGRURamKB": "58.7",
  "valDeployLSTMQemu": "5.070e-02",
  "valDeployLSTMKeilFps": "1426.3",
  "valDeployLSTMMae": "5.070e-02",
  "valDeployLSTMRamKB": "58.7",
  "valDeployLutQemu": "1.902e-04",
  "valDeployLutKeilFps": "3844.8",
  "valDeployLutMae": "1.902e-04",
  "valDeployLutRamKB": "5.6",
  "valDeployLutNearestQemu": "7.114e-03",
  "valDeployLutNearestKeilFps": "6986.7",
  "valDeployLutNearestMae": "7.114e-03",
  "valDeployLutNearestRamKB": "5.6",
  "valDeployLutInterpQemu": "1.902e-04",
  "valDeployLutInterpKeilFps": "3844.8",
  "valDeployLutInterpMae": "1.902e-04",
  "valDeployLutInterpRamKB": "5.6",
  "valDeployNoLutQemu": "6.517e-07",
  "valDeployNoLutKeilFps": "45.0",
  "valDeployNoLutMae": "6.517e-07",
  "valDeployNoLutRamKB": "21.2",
  "valHpBaseFreq": "2.34",
  "valHpBaseSens": "9.09",
  "valHpBaseLinearity": "0.511",
  "valHpCompleteAxes": "H_UNITS, INNER_KAN_UNITS, INNER_KAN_LAYERS, GRID_SIZE, SPLINE_ORDER",
  "valHpDominators": "1",
  "valHpHSet": "3, 4, 5, 6, 7, 8, 9, 10",
  "valHpHBase": "8",
  "valHpUSet": "3, 4, 5, 6, 7, 8",
  "valHpUBase": "6",
  "valHpLSet": "3, 4, 5, 6, 7, 8",
  "valHpLBase": "6",
  "valHpGridSet": "3, 4, 5, 6, 7, 8",
  "valHpOrderSet": "1, 2, 3",
  "valHpGridOrderBase": "8/2",
  "valHpHBestFreq": "8 (2.34 Hz)",
  "valHpHBestSens": "8 (9.09/%)",
  "valHpHBestLinearity": "8 (0.511/%)",
  "valHpUBestFreq": "8 (2.10 Hz)",
  "valHpUBestSens": "6 (9.09/%)",
  "valHpUBestLinearity": "6 (0.511/%)",
  "valHpLBestFreq": "7 (2.18 Hz)",
  "valHpLBestSens": "6 (9.09/%)",
  "valHpLBestLinearity": "7 (0.465/%)",
  "valHpGridBestFreq": "8 (2.34 Hz)",
  "valHpGridBestSens": "8 (9.09/%)",
  "valHpGridBestLinearity": "8 (0.511/%)",
  "valHpOrderBestFreq": "3 (2.28 Hz)",
  "valHpOrderBestSens": "2 (9.09/%)",
  "valHpOrderBestLinearity": "2 (0.511/%)",
  "valHpHBestMetric": "8 (0.511/%)",
  "valHpUBestMetric": "8 (2.10 Hz)",
  "valHpLBestMetric": "7 (0.465/%)",
  "valHpGridOrderSet": "grid=3, 4, 5, 6, 7, 8; order=1, 2, 3",
  "valHpSplineBestMetric": "3 (2.28 Hz)"
}