[
    {
        "name": "initial_conv/kernel:0",
        "shape": [
            8,
            1,
            8
        ],
        "config": {},
        "value": [
            [
                [
                    0.5325589179992676,
                    -0.7007264494895935,
                    -1.054977536201477,
                    0.8651660680770874,
                    0.9652882218360901,
                    -0.9473568797111511,
                    0.9265326857566833,
                    -0.44112086296081543
                ]
            ],
            [
                [
                    0.284623384475708,
                    -0.4456023871898651,
                    0.01204219926148653,
                    0.027443602681159973,
                    0.2493544965982437,
                    -0.3732850253582001,
                    0.023688582703471184,
                    -0.1994055211544037
                ]
            ],
            [
                [
                    -0.1715208739042282,
                    -0.3663875162601471,
                    0.4321524500846863,
                    -0.4470958113670349,
                    -0.09601670503616333,
                    -0.21717974543571472,
                    0.26129934191703796,
                    0.1445281058549881
                ]
            ],
            [
                [
                    -0.24233005940914154,
                    0.2888432741165161,
                    0.2727033495903015,
                    -0.5110223293304443,
                    0.04922261834144592,
                    -0.2523585259914398,
                    -0.3896152675151825,
                    0.5321732759475708
                ]
            ],
            [
                [
                    -0.5542176961898804,
                    0.8562959432601929,
                    0.3902551531791687,
                    -0.6456835865974426,
                    0.08495499193668365,
                    -0.2937503755092621,
                    -0.16511555016040802,
                    0.5598187446594238
                ]
            ],
            [
                [
                    -0.3051372468471527,
                    0.5339492559432983,
                    0.14049655199050903,
                    -0.41792866587638855,
                    -0.35231995582580566,
                    -0.20063893496990204,
                    0.8954305052757263,
                    0.4579160809516907
                ]
            ],
            [
                [
                    0.2822556495666504,
                    0.5090955495834351,
                    -0.05935288220643997,
                    -0.3062436282634735,
                    0.3310431241989136,
                    -0.2812338173389435,
                    0.47947272658348083,
                    0.037920188158750534
                ]
            ],
            [
                [
                    1.5092434883117676,
                    -0.46682924032211304,
                    -0.31411150097846985,
                    -0.19127076864242554,
                    0.45467323064804077,
                    -1.4767405986785889,
                    -3.511253595352173,
                    -1.1577305793762207
                ]
            ]
        ]
    },
    {
        "name": "initial_conv/bias:0",
        "shape": [
            8
        ],
        "config": {},
        "value": [
            0.010479331947863102,
            -0.004356816411018372,
            0.0012872316874563694,
            -0.00770634226500988,
            0.0013554359320551157,
            0.02277490310370922,
            0.02754521369934082,
            0.006527570076286793
        ]
    },
    {
        "name": "post_dense_1/kernel:0",
        "shape": [
            1,
            8,
            8
        ],
        "config": {},
        "value": [
            [
                [
                    1.0783284902572632,
                    -0.07394630461931229,
                    -0.777358889579773,
                    0.5156669020652771,
                    0.3056740462779999,
                    0.29664167761802673,
                    -0.7813982367515564,
                    -0.5795363783836365
                ],
                [
                    -2.289693593978882,
                    -0.03889740630984306,
                    0.11230553686618805,
                    -0.5179129242897034,
                    -1.3808873891830444,
                    -0.3569146990776062,
                    -0.8178178668022156,
                    0.15650039911270142
                ],
                [
                    0.47882285714149475,
                    -2.163907289505005,
                    0.019584503024816513,
                    -1.043533444404602,
                    0.5373635292053223,
                    0.1355506032705307,
                    1.097642183303833,
                    0.011832349933683872
                ],
                [
                    1.0621464252471924,
                    0.5806497931480408,
                    -0.7761787176132202,
                    0.9437502026557922,
                    0.46243810653686523,
                    -0.3350243866443634,
                    -0.13811111450195312,
                    0.10025989264249802
                ],
                [
                    -0.20979803800582886,
                    0.029707249253988266,
                    -0.2008771002292633,
                    0.08570277690887451,
                    0.24492087960243225,
                    0.08571615070104599,
                    -0.8129757642745972,
                    -0.10617417842149734
                ],
                [
                    0.3797237277030945,
                    -0.49925562739372253,
                    -0.28484979271888733,
                    -0.4038788974285126,
                    -0.4263557195663452,
                    -0.37844663858413696,
                    0.241056889295578,
                    0.9371573328971863
                ],
                [
                    -0.6612579226493835,
                    0.3952784240245819,
                    0.6593390107154846,
                    -0.007054726127535105,
                    0.10156719386577606,
                    -0.7752034068107605,
                    -0.7773787379264832,
                    0.9152149558067322
                ],
                [
                    -1.6932573318481445,
                    -0.022766364738345146,
                    1.126145839691162,
                    -1.8960579633712769,
                    -0.08982471376657486,
                    0.030846621841192245,
                    -0.02831519953906536,
                    0.04128953441977501
                ]
            ]
        ]
    },
    {
        "name": "post_dense_1/bias:0",
        "shape": [
            8
        ],
        "config": {},
        "value": [
            -0.04485675320029259,
            -0.5426435470581055,
            -0.08545701950788498,
            -0.1863555908203125,
            0.18760527670383453,
            0.036799799650907516,
            -0.27880409359931946,
            0.017252283170819283
        ]
    },
    {
        "name": "post_dense_2/kernel:0",
        "shape": [
            1,
            8,
            8
        ],
        "config": {},
        "value": [
            [
                [
                    -1.5273077487945557,
                    -1.8050764799118042,
                    -0.015698665753006935,
                    -0.8821849226951599,
                    -0.4258943796157837,
                    0.15343935787677765,
                    0.40908652544021606,
                    0.04099103808403015
                ],
                [
                    0.6775532364845276,
                    -7.156477451324463,
                    -0.5053281188011169,
                    0.7501006126403809,
                    0.33332252502441406,
                    0.8685805201530457,
                    1.0720713138580322,
                    -0.2291724979877472
                ],
                [
                    -0.005093684885650873,
                    -0.09984208643436432,
                    0.01812661625444889,
                    -3.786794424057007,
                    -0.3360244035720825,
                    -0.5105234980583191,
                    -0.4026625454425812,
                    0.5010876655578613
                ],
                [
                    1.6376879215240479,
                    0.8128222227096558,
                    -0.05667410418391228,
                    -1.1888656616210938,
                    -0.43622735142707825,
                    -1.0507123470306396,
                    0.0660162940621376,
                    -0.416579931974411
                ],
                [
                    0.30694064497947693,
                    -0.5004166960716248,
                    0.34074896574020386,
                    -0.13246798515319824,
                    0.18014302849769592,
                    -0.2207677811384201,
                    -1.027708888053894,
                    0.6376789212226868
                ],
                [
                    0.4374714493751526,
                    0.2545391023159027,
                    -0.24958685040473938,
                    0.11121676117181778,
                    -0.5674580931663513,
                    0.009215866215527058,
                    -0.8234967589378357,
                    -0.36690136790275574
                ],
                [
                    1.1158478260040283,
                    1.4917335510253906,
                    -0.1076684296131134,
                    0.5560527443885803,
                    0.07294735312461853,
                    -0.9189175367355347,
                    1.3683183193206787,
                    0.021668696776032448
                ],
                [
                    -0.5088809728622437,
                    0.17850427329540253,
                    0.6034777760505676,
                    0.8020435571670532,
                    -0.768757164478302,
                    0.38917139172554016,
                    -0.6897799968719482,
                    0.283537894487381
                ]
            ]
        ]
    },
    {
        "name": "post_dense_2/bias:0",
        "shape": [
            8
        ],
        "config": {},
        "value": [
            -0.0675896555185318,
            -0.044677574187517166,
            0.021773934364318848,
            -0.006053672172129154,
            -0.0856272503733635,
            -0.3950357139110565,
            0.21093817055225372,
            -0.22595630586147308
        ]
    },
    {
        "name": "dense/kernel:0",
        "shape": [
            8,
            1
        ],
        "config": {},
        "value": [
            [
                0.33489587903022766
            ],
            [
                -0.29077839851379395
            ],
            [
                -0.1725885570049286
            ],
            [
                -0.08311814069747925
            ],
            [
                -0.4880937337875366
            ],
            [
                0.16156502068042755
            ],
            [
                -0.06989184767007828
            ],
            [
                0.10761275142431259
            ]
        ]
    },
    {
        "name": "dense/bias:0",
        "shape": [
            1
        ],
        "config": {},
        "value": [
            0.021324491128325462
        ]
    }
]