[
    {
        "name": "simple_rnn/simple_rnn_cell/kernel:0",
        "shape": [
            1,
            4
        ],
        "config": {},
        "value": [
            [
                1.0183473825454712,
                0.0,
                1.0,
                0.0
            ]
        ]
    },
    {
        "name": "simple_rnn/simple_rnn_cell/recurrent_kernel:0",
        "shape": [
            4,
            4
        ],
        "config": {},
        "value": [
            [
                1.8204413652420044,
                1.0,
                0.0,
                0.0
            ],
            [
                -0.8312135934829712,
                0.0,
                0.0,
                0.0
            ],
            [
                -1.790741205215454,
                0.0,
                0.0,
                1.0
            ],
            [
                0.7836631536483765,
                0.0,
                0.0,
                0.0
            ]
        ]
    },
    {
        "name": "dense/kernel:0",
        "shape": [
            4,
            1
        ],
        "config": {},
        "value": [
            [
                1.0
            ],
            [
                0.0
            ],
            [
                0.0
            ],
            [
                0.0
            ]
        ]
    },
    {
        "name": "simple_rnn_1/simple_rnn_cell_1/kernel:0",
        "shape": [
            1,
            4
        ],
        "config": {},
        "value": [
            [
                0.9118178486824036,
                0.0,
                1.0,
                0.0
            ]
        ]
    },
    {
        "name": "simple_rnn_1/simple_rnn_cell_1/recurrent_kernel:0",
        "shape": [
            4,
            4
        ],
        "config": {},
        "value": [
            [
                1.8204413652420044,
                1.0,
                0.0,
                0.0
            ],
            [
                -0.8312135934829712,
                0.0,
                0.0,
                0.0
            ],
            [
                -1.6615842580795288,
                0.0,
                0.0,
                1.0
            ],
            [
                0.7607012391090393,
                0.0,
                0.0,
                0.0
            ]
        ]
    },
    {
        "name": "dense_1/kernel:0",
        "shape": [
            4,
            1
        ],
        "config": {},
        "value": [
            [
                1.0
            ],
            [
                0.0
            ],
            [
                0.0
            ],
            [
                0.0
            ]
        ]
    },
    {
        "name": "simple_rnn_2/simple_rnn_cell_2/kernel:0",
        "shape": [
            1,
            4
        ],
        "config": {},
        "value": [
            [
                0.5873786807060242,
                0.0,
                1.0,
                0.0
            ]
        ]
    },
    {
        "name": "simple_rnn_2/simple_rnn_cell_2/recurrent_kernel:0",
        "shape": [
            4,
            4
        ],
        "config": {},
        "value": [
            [
                1.8204413652420044,
                1.0,
                0.0,
                0.0
            ],
            [
                -0.8312135934829712,
                0.0,
                0.0,
                0.0
            ],
            [
                -1.044885277748108,
                0.0,
                0.0,
                1.0
            ],
            [
                0.4683836102485657,
                0.0,
                0.0,
                0.0
            ]
        ]
    },
    {
        "name": "dense_2/kernel:0",
        "shape": [
            4,
            1
        ],
        "config": {},
        "value": [
            [
                1.0
            ],
            [
                0.0
            ],
            [
                0.0
            ],
            [
                0.0
            ]
        ]
    },
    {
        "name": "simple_rnn_3/simple_rnn_cell_3/kernel:0",
        "shape": [
            1,
            4
        ],
        "config": {},
        "value": [
            [
                0.45533236861228943,
                0.0,
                1.0,
                0.0
            ]
        ]
    },
    {
        "name": "simple_rnn_3/simple_rnn_cell_3/recurrent_kernel:0",
        "shape": [
            4,
            4
        ],
        "config": {},
        "value": [
            [
                1.8204413652420044,
                1.0,
                0.0,
                0.0
            ],
            [
                -0.8312135934829712,
                0.0,
                0.0,
                0.0
            ],
            [
                -0.780312716960907,
                0.0,
                0.0,
                1.0
            ],
            [
                0.33610495924949646,
                0.0,
                0.0,
                0.0
            ]
        ]
    },
    {
        "name": "dense_3/kernel:0",
        "shape": [
            4,
            1
        ],
        "config": {},
        "value": [
            [
                1.0
            ],
            [
                0.0
            ],
            [
                0.0
            ],
            [
                0.0
            ]
        ]
    },
    {
        "name": "simple_rnn_4/simple_rnn_cell_4/kernel:0",
        "shape": [
            1,
            4
        ],
        "config": {},
        "value": [
            [
                0.3756066858768463,
                0.0,
                1.0,
                0.0
            ]
        ]
    },
    {
        "name": "simple_rnn_4/simple_rnn_cell_4/recurrent_kernel:0",
        "shape": [
            4,
            4
        ],
        "config": {},
        "value": [
            [
                1.8204413652420044,
                1.0,
                0.0,
                0.0
            ],
            [
                -0.8312135934829712,
                0.0,
                0.0,
                0.0
            ],
            [
                -0.617134153842926,
                0.0,
                0.0,
                1.0
            ],
            [
                0.25434568524360657,
                0.0,
                0.0,
                0.0
            ]
        ]
    },
    {
        "name": "dense_4/kernel:0",
        "shape": [
            4,
            1
        ],
        "config": {},
        "value": [
            [
                1.0
            ],
            [
                0.0
            ],
            [
                0.0
            ],
            [
                0.0
            ]
        ]
    },
    {
        "name": "simple_rnn_5/simple_rnn_cell_5/kernel:0",
        "shape": [
            1,
            4
        ],
        "config": {},
        "value": [
            [
                0.2986116409301758,
                0.0,
                1.0,
                0.0
            ]
        ]
    },
    {
        "name": "simple_rnn_5/simple_rnn_cell_5/recurrent_kernel:0",
        "shape": [
            4,
            4
        ],
        "config": {},
        "value": [
            [
                1.8204413652420044,
                1.0,
                0.0,
                0.0
            ],
            [
                -0.8312135934829712,
                0.0,
                0.0,
                0.0
            ],
            [
                -0.4729788899421692,
                0.0,
                0.0,
                1.0
            ],
            [
                0.18742403388023376,
                0.0,
                0.0,
                0.0
            ]
        ]
    },
    {
        "name": "dense_5/kernel:0",
        "shape": [
            4,
            1
        ],
        "config": {},
        "value": [
            [
                1.0
            ],
            [
                0.0
            ],
            [
                0.0
            ],
            [
                0.0
            ]
        ]
    },
    {
        "name": "simple_rnn_6/simple_rnn_cell_6/kernel:0",
        "shape": [
            1,
            4
        ],
        "config": {},
        "value": [
            [
                0.24232961237430573,
                0.0,
                1.0,
                0.0
            ]
        ]
    },
    {
        "name": "simple_rnn_6/simple_rnn_cell_6/recurrent_kernel:0",
        "shape": [
            4,
            4
        ],
        "config": {},
        "value": [
            [
                1.8204413652420044,
                1.0,
                0.0,
                0.0
            ],
            [
                -0.8312135934829712,
                0.0,
                0.0,
                0.0
            ],
            [
                -0.36367595195770264,
                0.0,
                0.0,
                1.0
            ],
            [
                0.13480040431022644,
                0.0,
                0.0,
                0.0
            ]
        ]
    },
    {
        "name": "dense_6/kernel:0",
        "shape": [
            4,
            1
        ],
        "config": {},
        "value": [
            [
                1.0
            ],
            [
                0.0
            ],
            [
                0.0
            ],
            [
                0.0
            ]
        ]
    },
    {
        "name": "simple_rnn_7/simple_rnn_cell_7/kernel:0",
        "shape": [
            1,
            4
        ],
        "config": {},
        "value": [
            [
                0.22203321754932404,
                0.0,
                1.0,
                0.0
            ]
        ]
    },
    {
        "name": "simple_rnn_7/simple_rnn_cell_7/recurrent_kernel:0",
        "shape": [
            4,
            4
        ],
        "config": {},
        "value": [
            [
                1.8204413652420044,
                1.0,
                0.0,
                0.0
            ],
            [
                -0.8312135934829712,
                0.0,
                0.0,
                0.0
            ],
            [
                -0.327933132648468,
                0.0,
                0.0,
                1.0
            ],
            [
                0.12066227942705154,
                0.0,
                0.0,
                0.0
            ]
        ]
    },
    {
        "name": "dense_7/kernel:0",
        "shape": [
            4,
            1
        ],
        "config": {},
        "value": [
            [
                1.0
            ],
            [
                0.0
            ],
            [
                0.0
            ],
            [
                0.0
            ]
        ]
    },
    {
        "name": "fridense_inner_0/kernel:0",
        "shape": [
            8,
            10
        ],
        "config": {},
        "value": [
            [
                0.3422296643257141,
                0.4996589422225952,
                -0.6875556111335754,
                -0.7559841275215149,
                -0.7419670820236206,
                0.45543503761291504,
                0.34339162707328796,
                -0.22303800284862518,
                -0.874762773513794,
                -0.13585533201694489
            ],
            [
                -0.992459774017334,
                0.5334959030151367,
                0.4321798086166382,
                -0.9486247897148132,
                -0.2932471036911011,
                -0.7007240056991577,
                0.41065889596939087,
                -0.45783427357673645,
                -0.07682961970567703,
                -0.5862023830413818
            ],
            [
                -0.511600911617279,
                0.13042275607585907,
                0.5574638843536377,
                -0.48011475801467896,
                0.006203224882483482,
                -0.24306774139404297,
                -0.5301507711410522,
                -0.44346868991851807,
                0.5299127101898193,
                -0.5234876275062561
            ],
            [
                -0.356171190738678,
                0.14570321142673492,
                0.45688310265541077,
                0.37322890758514404,
                0.06339221447706223,
                -0.5679595470428467,
                0.3797036409378052,
                0.37943795323371887,
                0.5195995569229126,
                -0.6742429137229919
            ],
            [
                -0.02603568509221077,
                -0.08948305249214172,
                0.16428321599960327,
                0.04313455894589424,
                -0.6124019622802734,
                0.5602987408638,
                0.09076601266860962,
                -0.5910354256629944,
                0.3945392370223999,
                0.1457487940788269
            ],
            [
                0.14788614213466644,
                0.020671453326940536,
                -0.6466779112815857,
                -0.17805349826812744,
                -0.6063498854637146,
                -0.1335134655237198,
                0.5213371515274048,
                -0.06687327474355698,
                -0.21955928206443787,
                -0.3158116638660431
            ],
            [
                0.7572663426399231,
                -0.4027159810066223,
                -0.26586082577705383,
                0.3505926728248596,
                0.07329556345939636,
                0.6034860014915466,
                0.33412960171699524,
                -0.0009206440881825984,
                0.21251414716243744,
                -0.43713662028312683
            ],
            [
                0.12357667088508606,
                -0.6257440447807312,
                0.5083816051483154,
                0.8795347213745117,
                -0.1264612078666687,
                -0.7977749705314636,
                -0.03537622466683388,
                -0.6670163869857788,
                0.49533072113990784,
                -0.2834184169769287
            ]
        ]
    },
    {
        "name": "fridense_inner_0/bias:0",
        "shape": [
            10
        ],
        "config": {},
        "value": [
            -0.030220292508602142,
            -0.0027352983597666025,
            0.03446877375245094,
            0.005692861042916775,
            0.021900366991758347,
            -0.0036860331892967224,
            0.002811178332194686,
            0.03182985261082649,
            0.02375844493508339,
            0.023618873208761215
        ]
    },
    {
        "name": "fridense_inner_1/kernel:0",
        "shape": [
            10,
            10
        ],
        "config": {},
        "value": [
            [
                -0.5694411396980286,
                0.5166783928871155,
                0.32415175437927246,
                0.26172441244125366,
                -0.4103012681007385,
                -0.27621451020240784,
                0.09442423284053802,
                -0.1687067151069641,
                0.30016547441482544,
                0.0032534669153392315
            ],
            [
                0.27521559596061707,
                0.5701602101325989,
                -0.17242081463336945,
                -0.07159554213285446,
                -0.4206685721874237,
                0.17461201548576355,
                -0.3215993344783783,
                -0.4634888172149658,
                0.5709566473960876,
                1.165507197380066
            ],
            [
                0.7955374121665955,
                0.7234494090080261,
                0.6954448819160461,
                -0.13681736588478088,
                0.7133888602256775,
                -0.2617108225822449,
                0.9582222700119019,
                -0.35523298382759094,
                0.4746153652667999,
                -0.6558692455291748
            ],
            [
                0.11087921261787415,
                -0.40521425008773804,
                0.9240686297416687,
                -0.5472161173820496,
                0.20519277453422546,
                -0.06599713116884232,
                0.30738022923469543,
                -0.5977281928062439,
                -0.19033747911453247,
                -0.09765134751796722
            ],
            [
                0.5761746764183044,
                -0.053725484758615494,
                0.46408599615097046,
                -0.4282780587673187,
                0.37700748443603516,
                0.5015490055084229,
                0.26022639870643616,
                0.2106969952583313,
                0.08731560409069061,
                0.5207105278968811
            ],
            [
                -0.9978263974189758,
                -0.6016780734062195,
                -0.16184550523757935,
                0.30821898579597473,
                -0.19994297623634338,
                -0.7516175508499146,
                -0.21265172958374023,
                0.5079208016395569,
                -0.7913892865180969,
                0.790368378162384
            ],
            [
                -0.23885205388069153,
                -0.31852632761001587,
                0.04645858705043793,
                -0.5332707166671753,
                0.29797860980033875,
                0.4714699983596802,
                0.1871219128370285,
                -0.36578911542892456,
                -0.30073031783103943,
                -0.7842193245887756
            ],
            [
                -0.27664774656295776,
                0.28605711460113525,
                0.27618956565856934,
                -0.47992467880249023,
                0.2071332037448883,
                -0.30638745427131653,
                -0.323885053396225,
                0.02428843080997467,
                0.12506362795829773,
                0.2686351537704468
            ],
            [
                0.6951960921287537,
                -0.30210989713668823,
                0.6711090803146362,
                -0.5020228028297424,
                -0.36003464460372925,
                1.0459117889404297,
                0.09441030770540237,
                -0.7696194052696228,
                0.31337735056877136,
                -0.43434327840805054
            ],
            [
                -0.04774947836995125,
                0.5885092616081238,
                -0.28008323907852173,
                0.49651482701301575,
                -0.24072322249412537,
                -0.050851330161094666,
                0.14763399958610535,
                0.4472329020500183,
                0.0448673851788044,
                0.5093679428100586
            ]
        ]
    },
    {
        "name": "fridense_inner_1/bias:0",
        "shape": [
            10
        ],
        "config": {},
        "value": [
            0.019826138392090797,
            9.06334025785327e-06,
            0.004017493221908808,
            -0.042575523257255554,
            0.055632334202528,
            -0.02979433164000511,
            -0.03788597136735916,
            0.030208762735128403,
            -0.005630194209516048,
            0.03230385482311249
        ]
    },
    {
        "name": "fridense_inner_2/kernel:0",
        "shape": [
            10,
            10
        ],
        "config": {},
        "value": [
            [
                -0.19405895471572876,
                0.8801984190940857,
                -0.5036300420761108,
                0.2437860518693924,
                0.5391337871551514,
                1.9051594734191895,
                0.49541446566581726,
                0.4810045659542084,
                0.4093605875968933,
                -0.09655839204788208
            ],
            [
                0.323379248380661,
                0.12656021118164062,
                -0.4634864926338196,
                0.4888204336166382,
                0.18707996606826782,
                0.4297192096710205,
                0.00043580468627624214,
                0.24169084429740906,
                0.49155235290527344,
                -0.370845764875412
            ],
            [
                -0.6046558618545532,
                0.3906886577606201,
                -0.12191697210073471,
                0.11344166100025177,
                0.383559912443161,
                -0.7173406481742859,
                0.13433414697647095,
                0.2644919157028198,
                0.032081954181194305,
                0.5245988368988037
            ],
            [
                -0.3251233696937561,
                0.18328392505645752,
                0.1173853874206543,
                -0.2125304490327835,
                -0.47446149587631226,
                -0.33428433537483215,
                -0.35346007347106934,
                0.3846895098686218,
                0.11391835659742355,
                0.4547411799430847
            ],
            [
                -0.3858911693096161,
                0.3815044164657593,
                -0.02235785312950611,
                0.14316539466381073,
                0.3115499019622803,
                -0.6127480268478394,
                0.2702508270740509,
                -0.13328389823436737,
                -0.45411136746406555,
                -0.32982468605041504
            ],
            [
                -0.2284841686487198,
                -0.27476343512535095,
                -0.2888026833534241,
                -0.13252286612987518,
                -0.4453308582305908,
                -0.10666976124048233,
                -2.2111942768096924,
                -0.8491509556770325,
                -1.7844997644424438,
                -0.32367828488349915
            ],
            [
                0.9327059388160706,
                -1.3265135288238525,
                0.12943154573440552,
                -0.3662678003311157,
                -0.5064828395843506,
                -0.21843986213207245,
                0.5498858690261841,
                0.5028651356697083,
                0.011675044894218445,
                -0.35117506980895996
            ],
            [
                0.4537625312805176,
                0.2738950550556183,
                -0.07112020999193192,
                0.5356544256210327,
                0.37160858511924744,
                -0.09577932208776474,
                -0.7446269989013672,
                -0.766633927822113,
                0.29623571038246155,
                -0.0610494539141655
            ],
            [
                -0.3520660400390625,
                -0.5936101675033569,
                -0.14552277326583862,
                -0.23885692656040192,
                0.3338029682636261,
                0.34020814299583435,
                0.578463077545166,
                0.965065062046051,
                0.674058198928833,
                -0.5040848851203918
            ],
            [
                0.3593418598175049,
                0.33652547001838684,
                0.04162455350160599,
                0.06711708754301071,
                -0.25098949670791626,
                0.4469555914402008,
                -0.18833708763122559,
                -0.23206685483455658,
                0.3156942129135132,
                0.7333229780197144
            ]
        ]
    },
    {
        "name": "fridense_inner_2/bias:0",
        "shape": [
            10
        ],
        "config": {},
        "value": [
            0.07044977694749832,
            0.03444032743573189,
            -0.0011879352387040854,
            0.150785893201828,
            0.020306499674916267,
            -0.3175877034664154,
            -0.06730838865041733,
            -0.05487349256873131,
            -0.03734389320015907,
            0.02601744420826435
        ]
    },
    {
        "name": "fridense_inner_3/kernel:0",
        "shape": [
            10,
            10
        ],
        "config": {},
        "value": [
            [
                -0.3296099603176117,
                0.3997775614261627,
                -0.014438452199101448,
                -0.6120637655258179,
                0.6188275218009949,
                -0.15786701440811157,
                0.0411076582968235,
                -0.09273040294647217,
                0.11548402905464172,
                -0.6753710508346558
            ],
            [
                0.3489978313446045,
                -0.17591996490955353,
                0.24333049356937408,
                -0.12524928152561188,
                -0.09139741212129593,
                -0.1725461781024933,
                0.4528638422489166,
                -0.0666179284453392,
                -0.2713043689727783,
                -0.0957542285323143
            ],
            [
                -0.19518157839775085,
                -0.13505280017852783,
                0.07851293683052063,
                0.16601347923278809,
                -0.3716452717781067,
                -0.06072762608528137,
                -0.44462499022483826,
                0.12134408950805664,
                0.18829989433288574,
                -0.20952239632606506
            ],
            [
                -0.449764221906662,
                -0.5288136601448059,
                0.4582270085811615,
                0.004415936768054962,
                0.49143892526626587,
                -0.4289722740650177,
                0.3469271957874298,
                -0.08881281316280365,
                -0.5742577314376831,
                0.11783888936042786
            ],
            [
                -0.7999131679534912,
                0.12960921227931976,
                0.16398043930530548,
                0.7383513450622559,
                -0.7213106155395508,
                0.1071440726518631,
                0.3291354775428772,
                0.48150479793548584,
                0.27894866466522217,
                0.5349836349487305
            ],
            [
                0.4123094975948334,
                -0.6915619969367981,
                0.3501555919647217,
                0.7065593004226685,
                -0.016469215974211693,
                0.42899155616760254,
                -0.24658232927322388,
                -2.2574198246002197,
                1.5340418815612793,
                1.546221375465393
            ],
            [
                0.41584447026252747,
                -2.22102427482605,
                0.9767179489135742,
                0.7581073045730591,
                -2.4001126289367676,
                -0.7451605796813965,
                0.14843909442424774,
                -0.13008534908294678,
                0.6796261668205261,
                0.8390942811965942
            ],
            [
                0.3638252019882202,
                0.7222679257392883,
                -0.03780335560441017,
                0.5558739900588989,
                -0.24126313626766205,
                -0.15697810053825378,
                0.8352219462394714,
                0.19100666046142578,
                0.9715719819068909,
                0.9000716209411621
            ],
            [
                0.07627835124731064,
                0.1018514335155487,
                0.34982064366340637,
                -0.15942859649658203,
                0.05904293432831764,
                0.1438688188791275,
                -0.2545391619205475,
                0.4186619520187378,
                0.37256792187690735,
                0.2614572048187256
            ],
            [
                -0.03969573974609375,
                -0.45757830142974854,
                -0.07516875863075256,
                0.29956355690956116,
                -0.569677472114563,
                0.18641017377376556,
                0.5312648415565491,
                0.2669839859008789,
                0.15360984206199646,
                -0.3427663743495941
            ]
        ]
    },
    {
        "name": "fridense_inner_3/bias:0",
        "shape": [
            10
        ],
        "config": {},
        "value": [
            -0.33510908484458923,
            0.13452403247356415,
            -0.0002166575432056561,
            -0.06385432928800583,
            -9.673960448708385e-05,
            0.08281026035547256,
            -0.016647418960928917,
            -0.06940852850675583,
            -0.03169715777039528,
            -0.03442731127142906
        ]
    },
    {
        "name": "fridense_inner_4/kernel:0",
        "shape": [
            10,
            10
        ],
        "config": {},
        "value": [
            [
                2.27603816986084,
                -0.31519755721092224,
                -0.8228430151939392,
                1.4679290056228638,
                1.8122479915618896,
                1.7418932914733887,
                -0.17874860763549805,
                2.015288829803467,
                0.22795461118221283,
                1.3383582830429077
            ],
            [
                -0.306521475315094,
                -0.1715313345193863,
                1.0445983409881592,
                -3.154808282852173,
                -0.3766922354698181,
                -0.20025238394737244,
                0.7809674143791199,
                1.2512459754943848,
                -0.16568730771541595,
                -0.33799248933792114
            ],
            [
                -0.29584500193595886,
                -0.4658595323562622,
                -0.5392899513244629,
                -0.07891275733709335,
                0.3121487498283386,
                0.5018860697746277,
                -0.9527212977409363,
                0.3806782364845276,
                0.023071156814694405,
                -0.412434846162796
            ],
            [
                -0.745733380317688,
                0.48853257298469543,
                -0.025938786566257477,
                -0.8055636286735535,
                -0.1278432160615921,
                0.20826303958892822,
                0.05412033200263977,
                -2.513735771179199,
                -0.08827631175518036,
                -0.5531330704689026
            ],
            [
                0.7226556539535522,
                -2.1252341270446777,
                -0.2696322798728943,
                0.35281383991241455,
                -0.43804582953453064,
                -0.34576088190078735,
                -0.4849502146244049,
                -0.4566771984100342,
                0.2504095435142517,
                0.16046954691410065
            ],
            [
                0.48530808091163635,
                0.8938079476356506,
                1.1276540756225586,
                0.002803362673148513,
                -1.154558777809143,
                0.3784484267234802,
                0.9954174160957336,
                0.8044681549072266,
                0.25312334299087524,
                0.21096567809581757
            ],
            [
                -0.12517429888248444,
                0.13846862316131592,
                0.2519785463809967,
                0.28720733523368835,
                0.5340451002120972,
                0.5660510063171387,
                -0.6771180033683777,
                -0.30657079815864563,
                -0.3260190784931183,
                0.7373006939888
            ],
            [
                -0.8757887482643127,
                0.22980132699012756,
                0.4556572139263153,
                -1.1405006647109985,
                -0.18746045231819153,
                -0.7671816945075989,
                0.363124817609787,
                0.3605596423149109,
                -0.3175273537635803,
                0.45042726397514343
            ],
            [
                0.46442723274230957,
                0.27188044786453247,
                -0.8015393018722534,
                0.1383284330368042,
                -0.8092111945152283,
                0.35129252076148987,
                0.08594000339508057,
                0.676343560218811,
                -0.26322323083877563,
                -0.4422365427017212
            ],
            [
                -0.11499994248151779,
                -0.7528060674667358,
                0.39844197034835815,
                -0.6776290535926819,
                0.5757431387901306,
                0.03196705877780914,
                0.3665344715118408,
                0.826272189617157,
                -0.014920626766979694,
                -0.01749257743358612
            ]
        ]
    },
    {
        "name": "fridense_inner_4/bias:0",
        "shape": [
            10
        ],
        "config": {},
        "value": [
            -0.01381248515099287,
            0.06194194033741951,
            0.10298171639442444,
            -0.026581574231386185,
            -0.030067935585975647,
            -0.02185440994799137,
            0.03294598311185837,
            -0.19341926276683807,
            -0.09619992971420288,
            0.02790885977447033
        ]
    },
    {
        "name": "fridense_inner_5/kernel:0",
        "shape": [
            10,
            10
        ],
        "config": {},
        "value": [
            [
                -0.22536002099514008,
                0.831208348274231,
                -0.4135473668575287,
                0.6625039577484131,
                0.08830484747886658,
                0.0876145139336586,
                0.21631008386611938,
                0.4822610914707184,
                0.6776959896087646,
                -0.9048528671264648
            ],
            [
                0.31757572293281555,
                0.1575094610452652,
                0.1941804438829422,
                1.1147898435592651,
                -0.1313321888446808,
                -0.31215396523475647,
                0.33640167117118835,
                0.35343682765960693,
                -0.9427186250686646,
                1.0105781555175781
            ],
            [
                0.5757734179496765,
                -0.5172521471977234,
                -0.5591305494308472,
                0.4651603400707245,
                -1.1806710958480835,
                0.06927206367254257,
                -0.5524996519088745,
                -0.12962578237056732,
                0.18565596640110016,
                0.34395501017570496
            ],
            [
                1.130496859550476,
                0.6005235910415649,
                -0.47387874126434326,
                0.9188408851623535,
                0.05596042424440384,
                0.1385253220796585,
                -0.4318581223487854,
                -0.20103979110717773,
                0.5723856687545776,
                0.049223653972148895
            ],
            [
                -0.5774020552635193,
                0.2580292820930481,
                -0.13033351302146912,
                -0.09811436384916306,
                -0.28397536277770996,
                0.5000438690185547,
                -0.4770396649837494,
                -0.4523232877254486,
                0.4428284764289856,
                0.33610332012176514
            ],
            [
                -0.6239917278289795,
                0.24227392673492432,
                0.011394765228033066,
                0.2620914578437805,
                0.22071869671344757,
                -0.05514488369226456,
                -0.4994090795516968,
                -0.5202751159667969,
                0.3871537446975708,
                -0.4649934470653534
            ],
            [
                1.2219510078430176,
                0.4822383224964142,
                -0.36175546050071716,
                0.9535970687866211,
                -0.02278350479900837,
                -6.146941661834717,
                0.3193846046924591,
                -0.08981036394834518,
                0.4168846309185028,
                0.8329008221626282
            ],
            [
                0.719407320022583,
                0.0037330740597099066,
                0.014740335755050182,
                -2.0387418270111084,
                -0.030452918261289597,
                0.5706062316894531,
                0.03298519551753998,
                -0.28986185789108276,
                0.19384190440177917,
                0.4714808166027069
            ],
            [
                0.19366388022899628,
                0.1013365387916565,
                0.2257700115442276,
                0.2501765787601471,
                -0.37792131304740906,
                -0.35776224732398987,
                -0.31034958362579346,
                0.05113307014107704,
                0.5130735039710999,
                0.5309605598449707
            ],
            [
                -0.17284122109413147,
                -0.17158739268779755,
                -0.4449555277824402,
                -0.44790294766426086,
                0.4099577069282532,
                -0.01837252266705036,
                -0.3516112267971039,
                0.39490947127342224,
                0.4224379062652588,
                -0.8893989324569702
            ]
        ]
    },
    {
        "name": "fridense_inner_5/bias:0",
        "shape": [
            10
        ],
        "config": {},
        "value": [
            0.07845054566860199,
            -0.024502405896782875,
            -0.11951925605535507,
            0.03263731300830841,
            -0.35169464349746704,
            -0.02551146410405636,
            -0.00256988569162786,
            -0.051357969641685486,
            -0.04170132428407669,
            0.03416414558887482
        ]
    },
    {
        "name": "final_dense/kernel:0",
        "shape": [
            10,
            1
        ],
        "config": {},
        "value": [
            [
                0.6349865198135376
            ],
            [
                -0.15532520413398743
            ],
            [
                0.25718438625335693
            ],
            [
                0.07277362048625946
            ],
            [
                -0.675711989402771
            ],
            [
                -0.4126121401786804
            ],
            [
                -0.3302733898162842
            ],
            [
                -0.21164290606975555
            ],
            [
                -0.16244003176689148
            ],
            [
                1.044522762298584
            ]
        ]
    },
    {
        "name": "final_dense/bias:0",
        "shape": [
            1
        ],
        "config": {},
        "value": [
            0.028132718056440353
        ]
    }
]